{
    "vodPic": "https://x.imgs.ovh/x/2023/09/05/64f680bb030b4.png",
    "drives": [
        {"name": "lao wang","server": "https://alist.jjww.eu.org"},
        {"name": "🔞罗汉果","server": "https://lala-ofbip.run.goorm.site/"},
		{"name": "pp","server": "https://yy.owen10089.repl.co/"},
        {
            "name": "範本",
            "server": "https://one.fongmi.com",
            "search": true,
            "hidden": false,
            "login": {
                "username": "fongmi",
                "password": "fongmi"
            },
            "params": [
                {
                    "path": "/安齋拉拉",
                    "pass": "18181818"
                }
            ]
        }
    ]
}
